{
  "5.0 Consent for menacwy" : {
    "transaction" : "5.0 Consent for menacwy",
    "sampleCount" : 1,
    "errorCount" : 0,
    "errorPct" : 0.0,
    "meanResTime" : 5231.0,
    "medianResTime" : 5231.0,
    "minResTime" : 5231.0,
    "maxResTime" : 5231.0,
    "pct1ResTime" : 5231.0,
    "pct2ResTime" : 5231.0,
    "pct3ResTime" : 5231.0,
    "throughput" : 0.19116803670426305,
    "receivedKBytesPerSec" : 43.69104407618046,
    "sentKBytesPerSec" : 3.065409338558593
  },
  "2.0 Register attendance" : {
    "transaction" : "2.0 Register attendance",
    "sampleCount" : 668,
    "errorCount" : 73,
    "errorPct" : 10.9281435,
    "meanResTime" : 9850.413173652696,
    "medianResTime" : 4866.5,
    "minResTime" : 448.0,
    "maxResTime" : 84306.0,
    "pct1ResTime" : 27266.000000000015,
    "pct2ResTime" : 42348.99999999998,
    "pct3ResTime" : 70227.7899999999,
    "throughput" : 0.1905952105820287,
    "receivedKBytesPerSec" : 38.514461030430326,
    "sentKBytesPerSec" : 0.770540666344966
  },
  "2.5 Select patient" : {
    "transaction" : "2.5 Select patient",
    "sampleCount" : 578,
    "errorCount" : 4,
    "errorPct" : 0.6920415,
    "meanResTime" : 682.6332179930791,
    "medianResTime" : 217.0,
    "minResTime" : 156.0,
    "maxResTime" : 26865.0,
    "pct1ResTime" : 556.0,
    "pct2ResTime" : 1358.6499999999994,
    "pct3ResTime" : 20884.210000000043,
    "throughput" : 0.16583538571359713,
    "receivedKBytesPerSec" : 4.695225285345173,
    "sentKBytesPerSec" : 0.11498351939126362
  },
  "1.4 Select Organisations" : {
    "transaction" : "1.4 Select Organisations",
    "sampleCount" : 70,
    "errorCount" : 0,
    "errorPct" : 0.0,
    "meanResTime" : 241.24285714285713,
    "medianResTime" : 230.0,
    "minResTime" : 216.0,
    "maxResTime" : 371.0,
    "pct1ResTime" : 271.8,
    "pct2ResTime" : 324.45000000000005,
    "pct3ResTime" : 371.0,
    "throughput" : 0.07912501299910928,
    "receivedKBytesPerSec" : 1.1368811682186473,
    "sentKBytesPerSec" : 0.11436037035027512
  },
  "2.5 Select menacwy" : {
    "transaction" : "2.5 Select menacwy",
    "sampleCount" : 370,
    "errorCount" : 1,
    "errorPct" : 0.27027026,
    "meanResTime" : 332.7945945945944,
    "medianResTime" : 226.0,
    "minResTime" : 158.0,
    "maxResTime" : 3650.0,
    "pct1ResTime" : 483.7000000000001,
    "pct2ResTime" : 586.4999999999999,
    "pct3ResTime" : 2365.260000000002,
    "throughput" : 0.11333763403706815,
    "receivedKBytesPerSec" : 2.857231643189695,
    "sentKBytesPerSec" : 0.0790264362328776
  },
  "2.3 Search by first/last name" : {
    "transaction" : "2.3 Search by first/last name",
    "sampleCount" : 629,
    "errorCount" : 13,
    "errorPct" : 2.0667727,
    "meanResTime" : 1566.163751987281,
    "medianResTime" : 713.0,
    "minResTime" : 447.0,
    "maxResTime" : 36554.0,
    "pct1ResTime" : 1567.0,
    "pct2ResTime" : 4335.5,
    "pct3ResTime" : 24500.30000000001,
    "throughput" : 0.17882160824592208,
    "receivedKBytesPerSec" : 10.553124883172488,
    "sentKBytesPerSec" : 0.1542503505536078
  },
  "2.5 Select td_ipv" : {
    "transaction" : "2.5 Select td_ipv",
    "sampleCount" : 317,
    "errorCount" : 2,
    "errorPct" : 0.6309148,
    "meanResTime" : 528.9274447949526,
    "medianResTime" : 228.0,
    "minResTime" : 159.0,
    "maxResTime" : 29508.0,
    "pct1ResTime" : 563.1999999999999,
    "pct2ResTime" : 846.3999999999995,
    "pct3ResTime" : 7912.2599999999675,
    "throughput" : 0.10001110533409388,
    "receivedKBytesPerSec" : 2.544274348937958,
    "sentKBytesPerSec" : 0.06963663877266497
  },
  "4.0 Vaccination for flu" : {
    "transaction" : "4.0 Vaccination for flu",
    "sampleCount" : 562,
    "errorCount" : 24,
    "errorPct" : 4.2704625,
    "meanResTime" : 2174.989323843416,
    "medianResTime" : 1495.5,
    "minResTime" : 514.0,
    "maxResTime" : 36469.0,
    "pct1ResTime" : 3242.7999999999993,
    "pct2ResTime" : 4978.900000000006,
    "pct3ResTime" : 18624.750000000004,
    "throughput" : 0.16351878458407745,
    "receivedKBytesPerSec" : 8.704620832271333,
    "sentKBytesPerSec" : 0.978712298300161
  },
  "4.0 Vaccination for hpv" : {
    "transaction" : "4.0 Vaccination for hpv",
    "sampleCount" : 533,
    "errorCount" : 16,
    "errorPct" : 3.001876,
    "meanResTime" : 2295.6622889305804,
    "medianResTime" : 1530.0,
    "minResTime" : 703.0,
    "maxResTime" : 49711.0,
    "pct1ResTime" : 3069.2000000000003,
    "pct2ResTime" : 4600.699999999995,
    "pct3ResTime" : 23023.779999999915,
    "throughput" : 0.16056301284895722,
    "receivedKBytesPerSec" : 8.195365144729632,
    "sentKBytesPerSec" : 0.9683809620691722
  },
  "5.8 Consent confirm" : {
    "transaction" : "5.8 Consent confirm",
    "sampleCount" : 4,
    "errorCount" : 0,
    "errorPct" : 0.0,
    "meanResTime" : 1127.0,
    "medianResTime" : 1159.0,
    "minResTime" : 853.0,
    "maxResTime" : 1337.0,
    "pct1ResTime" : 1337.0,
    "pct2ResTime" : 1337.0,
    "pct3ResTime" : 1337.0,
    "throughput" : 0.006521615077974061,
    "receivedKBytesPerSec" : 0.6494213467746537,
    "sentKBytesPerSec" : 0.014423659910001711
  },
  "Select Organisations" : {
    "transaction" : "Select Organisations",
    "sampleCount" : 1,
    "errorCount" : 0,
    "errorPct" : 0.0,
    "meanResTime" : 0.0,
    "medianResTime" : 0.0,
    "minResTime" : 0.0,
    "maxResTime" : 0.0,
    "pct1ResTime" : 0.0,
    "pct2ResTime" : 0.0,
    "pct3ResTime" : 0.0,
    "throughput" : "Infinity",
    "receivedKBytesPerSec" : "NaN",
    "sentKBytesPerSec" : "NaN"
  },
  "1.2 Sign-in page" : {
    "transaction" : "1.2 Sign-in page",
    "sampleCount" : 70,
    "errorCount" : 0,
    "errorPct" : 0.0,
    "meanResTime" : 94.18571428571428,
    "medianResTime" : 91.0,
    "minResTime" : 86.0,
    "maxResTime" : 123.0,
    "pct1ResTime" : 114.6,
    "pct2ResTime" : 121.45,
    "pct3ResTime" : 123.0,
    "throughput" : 0.07900819879365767,
    "receivedKBytesPerSec" : 0.47613241675357565,
    "sentKBytesPerSec" : 0.047605526030944124
  },
  "5.9 Patient home page" : {
    "transaction" : "5.9 Patient home page",
    "sampleCount" : 4,
    "errorCount" : 0,
    "errorPct" : 0.0,
    "meanResTime" : 269.5,
    "medianResTime" : 223.0,
    "minResTime" : 188.0,
    "maxResTime" : 444.0,
    "pct1ResTime" : 444.0,
    "pct2ResTime" : 444.0,
    "pct3ResTime" : 444.0,
    "throughput" : 0.00648684063292104,
    "receivedKBytesPerSec" : 0.1681431535248681,
    "sentKBytesPerSec" : 0.004844542357447622
  },
  "2.4 Patient attending session" : {
    "transaction" : "2.4 Patient attending session",
    "sampleCount" : 596,
    "errorCount" : 16,
    "errorPct" : 2.6845639,
    "meanResTime" : 2209.4362416107388,
    "medianResTime" : 905.0,
    "minResTime" : 450.0,
    "maxResTime" : 40626.0,
    "pct1ResTime" : 2428.600000000002,
    "pct2ResTime" : 7894.749999999961,
    "pct3ResTime" : 31172.469999999987,
    "throughput" : 0.1702006139787249,
    "receivedKBytesPerSec" : 9.013853285410866,
    "sentKBytesPerSec" : 0.25125718390804597
  },
  "Logout" : {
    "transaction" : "Logout",
    "sampleCount" : 1,
    "errorCount" : 0,
    "errorPct" : 0.0,
    "meanResTime" : 328.0,
    "medianResTime" : 328.0,
    "minResTime" : 328.0,
    "maxResTime" : 328.0,
    "pct1ResTime" : 328.0,
    "pct2ResTime" : 328.0,
    "pct3ResTime" : 328.0,
    "throughput" : 3.048780487804878,
    "receivedKBytesPerSec" : 19.12037919207317,
    "sentKBytesPerSec" : 6.445907964939024
  },
  "5.4 Consent route" : {
    "transaction" : "5.4 Consent route",
    "sampleCount" : 4,
    "errorCount" : 0,
    "errorPct" : 0.0,
    "meanResTime" : 638.25,
    "medianResTime" : 380.5,
    "minResTime" : 321.0,
    "maxResTime" : 1471.0,
    "pct1ResTime" : 1471.0,
    "pct2ResTime" : 1471.0,
    "pct3ResTime" : 1471.0,
    "throughput" : 0.006568457282859118,
    "receivedKBytesPerSec" : 0.07742793529987471,
    "sentKBytesPerSec" : 0.010473289676355689
  },
  "1.1 Homepage" : {
    "transaction" : "1.1 Homepage",
    "sampleCount" : 70,
    "errorCount" : 0,
    "errorPct" : 0.0,
    "meanResTime" : 279.3,
    "medianResTime" : 263.5,
    "minResTime" : 249.0,
    "maxResTime" : 498.0,
    "pct1ResTime" : 331.7,
    "pct2ResTime" : 354.15000000000003,
    "pct3ResTime" : 498.0,
    "throughput" : 0.07890720287492757,
    "receivedKBytesPerSec" : 0.407250553900383,
    "sentKBytesPerSec" : 0.042767087495688284
  },
  "1.3 Sign-in" : {
    "transaction" : "1.3 Sign-in",
    "sampleCount" : 70,
    "errorCount" : 0,
    "errorPct" : 0.0,
    "meanResTime" : 557.3714285714285,
    "medianResTime" : 494.0,
    "minResTime" : 416.0,
    "maxResTime" : 1868.0,
    "pct1ResTime" : 745.0999999999999,
    "pct2ResTime" : 913.3000000000002,
    "pct3ResTime" : 1868.0,
    "throughput" : 0.07905950809174066,
    "receivedKBytesPerSec" : 0.7672014960035419,
    "sentKBytesPerSec" : 0.12437975345292401
  },
  "4.0 Vaccination for td_ipv" : {
    "transaction" : "4.0 Vaccination for td_ipv",
    "sampleCount" : 308,
    "errorCount" : 12,
    "errorPct" : 3.8961039,
    "meanResTime" : 2378.1590909090905,
    "medianResTime" : 1533.5,
    "minResTime" : 620.0,
    "maxResTime" : 45338.0,
    "pct1ResTime" : 3333.4,
    "pct2ResTime" : 4597.400000000001,
    "pct3ResTime" : 31322.530000000144,
    "throughput" : 0.09860016576352544,
    "receivedKBytesPerSec" : 5.470150508010944,
    "sentKBytesPerSec" : 0.5947053841853017
  },
  "2.1 Open session" : {
    "transaction" : "2.1 Open session",
    "sampleCount" : 669,
    "errorCount" : 19,
    "errorPct" : 2.8400598,
    "meanResTime" : 3850.8340807174886,
    "medianResTime" : 1933.0,
    "minResTime" : 449.0,
    "maxResTime" : 35856.0,
    "pct1ResTime" : 6840.0,
    "pct2ResTime" : 20964.5,
    "pct3ResTime" : 30307.099999999995,
    "throughput" : 0.18994366140398747,
    "receivedKBytesPerSec" : 3.258960499952159,
    "sentKBytesPerSec" : 0.12417834150010632
  },
  "4.3 Vaccination confirm" : {
    "transaction" : "4.3 Vaccination confirm",
    "sampleCount" : 1696,
    "errorCount" : 31,
    "errorPct" : 1.8278302,
    "meanResTime" : 1117.9139150943377,
    "medianResTime" : 800.0,
    "minResTime" : 449.0,
    "maxResTime" : 47279.0,
    "pct1ResTime" : 1435.6,
    "pct2ResTime" : 2226.5999999999995,
    "pct3ResTime" : 6797.659999999956,
    "throughput" : 0.4993696047619131,
    "receivedKBytesPerSec" : 10.339964569159745,
    "sentKBytesPerSec" : 1.1550791746312585
  },
  "5.6 Consent questions" : {
    "transaction" : "5.6 Consent questions",
    "sampleCount" : 4,
    "errorCount" : 0,
    "errorPct" : 0.0,
    "meanResTime" : 348.5,
    "medianResTime" : 317.0,
    "minResTime" : 269.0,
    "maxResTime" : 491.0,
    "pct1ResTime" : 491.0,
    "pct2ResTime" : 491.0,
    "pct3ResTime" : 491.0,
    "throughput" : 0.006568791670772161,
    "receivedKBytesPerSec" : 0.08044364233339901,
    "sentKBytesPerSec" : 0.01643961997487437
  },
  "4.1 Vaccination questions" : {
    "transaction" : "4.1 Vaccination questions",
    "sampleCount" : 1761,
    "errorCount" : 18,
    "errorPct" : 1.0221465,
    "meanResTime" : 585.610448608745,
    "medianResTime" : 413.0,
    "minResTime" : 237.0,
    "maxResTime" : 26047.0,
    "pct1ResTime" : 595.0,
    "pct2ResTime" : 1219.7999999999997,
    "pct3ResTime" : 4457.579999999989,
    "throughput" : 0.511110633829429,
    "receivedKBytesPerSec" : 6.073522528195254,
    "sentKBytesPerSec" : 1.101772224786805
  },
  "5.3 Consent parent details" : {
    "transaction" : "5.3 Consent parent details",
    "sampleCount" : 4,
    "errorCount" : 0,
    "errorPct" : 0.0,
    "meanResTime" : 325.5,
    "medianResTime" : 288.5,
    "minResTime" : 269.0,
    "maxResTime" : 456.0,
    "pct1ResTime" : 456.0,
    "pct2ResTime" : 456.0,
    "pct3ResTime" : 456.0,
    "throughput" : 0.0065709822139938924,
    "receivedKBytesPerSec" : 0.07427648352244073,
    "sentKBytesPerSec" : 0.012126478162983357
  },
  "Homepage" : {
    "transaction" : "Homepage",
    "sampleCount" : 1,
    "errorCount" : 0,
    "errorPct" : 0.0,
    "meanResTime" : 0.0,
    "medianResTime" : 0.0,
    "minResTime" : 0.0,
    "maxResTime" : 0.0,
    "pct1ResTime" : 0.0,
    "pct2ResTime" : 0.0,
    "pct3ResTime" : 0.0,
    "throughput" : "Infinity",
    "receivedKBytesPerSec" : "NaN",
    "sentKBytesPerSec" : "NaN"
  },
  "Sign In Page" : {
    "transaction" : "Sign In Page",
    "sampleCount" : 1,
    "errorCount" : 0,
    "errorPct" : 0.0,
    "meanResTime" : 0.0,
    "medianResTime" : 0.0,
    "minResTime" : 0.0,
    "maxResTime" : 0.0,
    "pct1ResTime" : 0.0,
    "pct2ResTime" : 0.0,
    "pct3ResTime" : 0.0,
    "throughput" : "Infinity",
    "receivedKBytesPerSec" : "NaN",
    "sentKBytesPerSec" : "NaN"
  },
  "5.2 Consent who" : {
    "transaction" : "5.2 Consent who",
    "sampleCount" : 4,
    "errorCount" : 0,
    "errorPct" : 0.0,
    "meanResTime" : 530.75,
    "medianResTime" : 473.0,
    "minResTime" : 328.0,
    "maxResTime" : 849.0,
    "pct1ResTime" : 849.0,
    "pct2ResTime" : 849.0,
    "pct3ResTime" : 849.0,
    "throughput" : 0.006626685663165568,
    "receivedKBytesPerSec" : 0.14055012621765348,
    "sentKBytesPerSec" : 0.01057260517792651
  },
  "1.0 Login" : {
    "transaction" : "1.0 Login",
    "sampleCount" : 70,
    "errorCount" : 0,
    "errorPct" : 0.0,
    "meanResTime" : 1343.3857142857144,
    "medianResTime" : 1286.5,
    "minResTime" : 1146.0,
    "maxResTime" : 2632.0,
    "pct1ResTime" : 1575.5,
    "pct2ResTime" : 1755.9,
    "pct3ResTime" : 2632.0,
    "throughput" : 0.07879652935058151,
    "receivedKBytesPerSec" : 3.641338442772332,
    "sentKBytesPerSec" : 0.3751299615078954
  },
  "4.0 Vaccination for menacwy" : {
    "transaction" : "4.0 Vaccination for menacwy",
    "sampleCount" : 350,
    "errorCount" : 10,
    "errorPct" : 2.857143,
    "meanResTime" : 2007.6057142857144,
    "medianResTime" : 1534.5,
    "minResTime" : 541.0,
    "maxResTime" : 27962.0,
    "pct1ResTime" : 2912.000000000001,
    "pct2ResTime" : 3764.249999999999,
    "pct3ResTime" : 18582.63000000015,
    "throughput" : 0.10858841268560862,
    "receivedKBytesPerSec" : 5.56800386914088,
    "sentKBytesPerSec" : 0.6416611709941735
  },
  "5.0 Consent for td_ipv" : {
    "transaction" : "5.0 Consent for td_ipv",
    "sampleCount" : 1,
    "errorCount" : 0,
    "errorPct" : 0.0,
    "meanResTime" : 4487.0,
    "medianResTime" : 4487.0,
    "minResTime" : 4487.0,
    "maxResTime" : 4487.0,
    "pct1ResTime" : 4487.0,
    "pct2ResTime" : 4487.0,
    "pct3ResTime" : 4487.0,
    "throughput" : 0.22286605749944285,
    "receivedKBytesPerSec" : 51.01173354969913,
    "sentKBytesPerSec" : 3.5730391269222195
  },
  "Calculate site depending on vaccination" : {
    "transaction" : "Calculate site depending on vaccination",
    "sampleCount" : 1786,
    "errorCount" : 0,
    "errorPct" : 0.0,
    "meanResTime" : 0.21332586786114216,
    "medianResTime" : 0.0,
    "minResTime" : 0.0,
    "maxResTime" : 27.0,
    "pct1ResTime" : 1.0,
    "pct2ResTime" : 1.0,
    "pct3ResTime" : 1.0,
    "throughput" : 0.5127887092310006,
    "receivedKBytesPerSec" : 0.0,
    "sentKBytesPerSec" : 0.0
  },
  "Login" : {
    "transaction" : "Login",
    "sampleCount" : 1,
    "errorCount" : 0,
    "errorPct" : 0.0,
    "meanResTime" : 0.0,
    "medianResTime" : 0.0,
    "minResTime" : 0.0,
    "maxResTime" : 0.0,
    "pct1ResTime" : 0.0,
    "pct2ResTime" : 0.0,
    "pct3ResTime" : 0.0,
    "throughput" : "Infinity",
    "receivedKBytesPerSec" : "NaN",
    "sentKBytesPerSec" : "NaN"
  },
  "Calculate slug from API" : {
    "transaction" : "Calculate slug from API",
    "sampleCount" : 1,
    "errorCount" : 0,
    "errorPct" : 0.0,
    "meanResTime" : 0.0,
    "medianResTime" : 0.0,
    "minResTime" : 0.0,
    "maxResTime" : 0.0,
    "pct1ResTime" : 0.0,
    "pct2ResTime" : 0.0,
    "pct3ResTime" : 0.0,
    "throughput" : "Infinity",
    "receivedKBytesPerSec" : "NaN",
    "sentKBytesPerSec" : "NaN"
  },
  "2.5 Select hpv" : {
    "transaction" : "2.5 Select hpv",
    "sampleCount" : 535,
    "errorCount" : 1,
    "errorPct" : 0.18691589,
    "meanResTime" : 407.343925233645,
    "medianResTime" : 237.0,
    "minResTime" : 158.0,
    "maxResTime" : 16077.0,
    "pct1ResTime" : 505.60000000000014,
    "pct2ResTime" : 685.0,
    "pct3ResTime" : 3110.5999999999985,
    "throughput" : 0.1597583378921694,
    "receivedKBytesPerSec" : 3.826799505040301,
    "sentKBytesPerSec" : 0.11903868340988794
  },
  "2.5 Select flu" : {
    "transaction" : "2.5 Select flu",
    "sampleCount" : 574,
    "errorCount" : 5,
    "errorPct" : 0.87108016,
    "meanResTime" : 718.0662020905924,
    "medianResTime" : 249.0,
    "minResTime" : 153.0,
    "maxResTime" : 25350.0,
    "pct1ResTime" : 542.5,
    "pct2ResTime" : 654.5,
    "pct3ResTime" : 23817.25,
    "throughput" : 0.16479317308393485,
    "receivedKBytesPerSec" : 3.8840499560527615,
    "sentKBytesPerSec" : 0.11426089149374388
  },
  "5.1 Consent start" : {
    "transaction" : "5.1 Consent start",
    "sampleCount" : 5,
    "errorCount" : 0,
    "errorPct" : 0.0,
    "meanResTime" : 591.8,
    "medianResTime" : 587.0,
    "minResTime" : 462.0,
    "maxResTime" : 688.0,
    "pct1ResTime" : 688.0,
    "pct2ResTime" : 688.0,
    "pct3ResTime" : 688.0,
    "throughput" : 0.003042513651758755,
    "receivedKBytesPerSec" : 0.03957882407455862,
    "sentKBytesPerSec" : 0.006566956712028517
  },
  "5.5 Consent agree" : {
    "transaction" : "5.5 Consent agree",
    "sampleCount" : 4,
    "errorCount" : 0,
    "errorPct" : 0.0,
    "meanResTime" : 410.0,
    "medianResTime" : 374.5,
    "minResTime" : 363.0,
    "maxResTime" : 528.0,
    "pct1ResTime" : 528.0,
    "pct2ResTime" : 528.0,
    "pct3ResTime" : 528.0,
    "throughput" : 0.006570885065363879,
    "receivedKBytesPerSec" : 0.11120773791532101,
    "sentKBytesPerSec" : 0.010355240013897423
  },
  "1.5 Open Sessions list" : {
    "transaction" : "1.5 Open Sessions list",
    "sampleCount" : 88,
    "errorCount" : 0,
    "errorPct" : 0.0,
    "meanResTime" : 558.9886363636363,
    "medianResTime" : 145.0,
    "minResTime" : 134.0,
    "maxResTime" : 29539.0,
    "pct1ResTime" : 275.20000000000005,
    "pct2ResTime" : 392.4999999999998,
    "pct3ResTime" : 29539.0,
    "throughput" : 0.02635528299134858,
    "receivedKBytesPerSec" : 0.28864697143356866,
    "sentKBytesPerSec" : 0.016030418376640355
  },
  "Total" : {
    "transaction" : "Total",
    "sampleCount" : 12305,
    "errorCount" : 144,
    "errorPct" : 1.170256,
    "meanResTime" : 934.7835839089811,
    "medianResTime" : 421.0,
    "minResTime" : 0.0,
    "maxResTime" : 47279.0,
    "pct1ResTime" : 1426.0,
    "pct2ResTime" : 2426.8999999999924,
    "pct3ResTime" : 18585.42000000002,
    "throughput" : 3.4141814080411534,
    "receivedKBytesPerSec" : 76.38085525911916,
    "sentKBytesPerSec" : 4.135340902666696
  },
  "4.2 Vaccination batch" : {
    "transaction" : "4.2 Vaccination batch",
    "sampleCount" : 1737,
    "errorCount" : 13,
    "errorPct" : 0.7484168,
    "meanResTime" : 551.1542890040298,
    "medianResTime" : 292.0,
    "minResTime" : 227.0,
    "maxResTime" : 30810.0,
    "pct1ResTime" : 552.2,
    "pct2ResTime" : 1225.4999999999995,
    "pct3ResTime" : 3831.459999999991,
    "throughput" : 0.5051653667698325,
    "receivedKBytesPerSec" : 10.541868356253842,
    "sentKBytesPerSec" : 0.8159803461735105
  },
  "5.0 Consent for hpv" : {
    "transaction" : "5.0 Consent for hpv",
    "sampleCount" : 1,
    "errorCount" : 0,
    "errorPct" : 0.0,
    "meanResTime" : 4753.0,
    "medianResTime" : 4753.0,
    "minResTime" : 4753.0,
    "maxResTime" : 4753.0,
    "pct1ResTime" : 4753.0,
    "pct2ResTime" : 4753.0,
    "pct3ResTime" : 4753.0,
    "throughput" : 0.21039343572480537,
    "receivedKBytesPerSec" : 47.49529080317694,
    "sentKBytesPerSec" : 3.371226067746686
  },
  "5.7 Consent triage" : {
    "transaction" : "5.7 Consent triage",
    "sampleCount" : 4,
    "errorCount" : 0,
    "errorPct" : 0.0,
    "meanResTime" : 475.0,
    "medianResTime" : 398.5,
    "minResTime" : 365.0,
    "maxResTime" : 738.0,
    "pct1ResTime" : 738.0,
    "pct2ResTime" : 738.0,
    "pct3ResTime" : 738.0,
    "throughput" : 0.006543314286835997,
    "receivedKBytesPerSec" : 0.10660043026381007,
    "sentKBytesPerSec" : 0.011048232814393983
  },
  "5.0 Consent for flu" : {
    "transaction" : "5.0 Consent for flu",
    "sampleCount" : 1,
    "errorCount" : 0,
    "errorPct" : 0.0,
    "meanResTime" : 4399.0,
    "medianResTime" : 4399.0,
    "minResTime" : 4399.0,
    "maxResTime" : 4399.0,
    "pct1ResTime" : 4399.0,
    "pct2ResTime" : 4399.0,
    "pct3ResTime" : 4399.0,
    "throughput" : 0.22732439190725165,
    "receivedKBytesPerSec" : 51.86814474880655,
    "sentKBytesPerSec" : 3.5506116446919753
  },
  "Log name and address" : {
    "transaction" : "Log name and address",
    "sampleCount" : 1,
    "errorCount" : 0,
    "errorPct" : 0.0,
    "meanResTime" : 75.0,
    "medianResTime" : 75.0,
    "minResTime" : 75.0,
    "maxResTime" : 75.0,
    "pct1ResTime" : 75.0,
    "pct2ResTime" : 75.0,
    "pct3ResTime" : 75.0,
    "throughput" : 13.333333333333334,
    "receivedKBytesPerSec" : 0.0,
    "sentKBytesPerSec" : 0.0
  },
  "2.2 Session register" : {
    "transaction" : "2.2 Session register",
    "sampleCount" : 650,
    "errorCount" : 21,
    "errorPct" : 3.2307692,
    "meanResTime" : 1958.1876923076932,
    "medianResTime" : 781.5,
    "minResTime" : 448.0,
    "maxResTime" : 33900.0,
    "pct1ResTime" : 2681.8,
    "pct2ResTime" : 7356.09999999999,
    "pct3ResTime" : 27432.600000000013,
    "throughput" : 0.1845863051728466,
    "receivedKBytesPerSec" : 10.894478689493319,
    "sentKBytesPerSec" : 0.12226901455477215
  }
}